pmcu/__about__.py
pmcu/__init__.py
pmcu/flags.py
pmcu/hash.py
pmcu/install_plugin.py
pmcu/main.py
pmcu/paper.py
pmcu/providers.py
pmcu/updatePlugins.py
pmcu/vars.py
pmcu/static/base.json
pmcu-1.1.0.dist-info/METADATA
pmcu-1.1.0.dist-info/WHEEL
pmcu-1.1.0.dist-info/entry_points.txt
pmcu-1.1.0.dist-info/licenses/LICENSE
pmcu-1.1.0.dist-info/RECORD
