Metadata-Version: 2.4
Name: pmcu
Version: 1.1.0
Summary: Minecraft server manager
Project-URL: Documentation, https://papermc-updater.readthedocs.io/
Project-URL: Source code, https://github.com/transdryad/PaperMC-Updater
Author-email: Hazel Viswanath <viswanath.hazel@gmail.com>
License-File: LICENSE
Requires-Python: >=3.13.2
Requires-Dist: requests>=2.32.3
